fastapi_provider_postmark/__init__.py
fastapi_provider_postmark/provider.py
fastapi_provider_postmark-0.1.2.dist-info/licenses/LICENSE
fastapi_provider_postmark-0.1.2.dist-info/METADATA
fastapi_provider_postmark-0.1.2.dist-info/WHEEL
fastapi_provider_postmark-0.1.2.dist-info/top_level.txt
fastapi_provider_postmark-0.1.2.dist-info/RECORD
