Metadata-Version: 2.4
Name: fastapi-provider-postmark
Version: 0.1.2
Summary: Postmark email provider for FastAPI projects.
Requires-Python: >=3.12
License-File: LICENSE
Requires-Dist: fastapi[standard]==0.128
Requires-Dist: postmarker>=1.0.0
Requires-Dist: pytest>=9.0.1
Requires-Dist: pytest-asyncio>=0.25.3
Provides-Extra: dev
Dynamic: license-file
